MANIFEST.in
README.md
etcpack.cpp
etcpack.h
etcpack.pxd
etcpack.pyx
setup.cfg
setup.py
etcpack.egg-info/PKG-INFO
etcpack.egg-info/SOURCES.txt
etcpack.egg-info/dependency_links.txt
etcpack.egg-info/top_level.txt
etcpack/source/etcdec.cxx
etcpack/source/etcpack.cxx
etcpack/source/image.cxx
etcpack/source/etcdec.cxx
etcpack/source/etcpack.cxx
etcpack/source/image.cxx
etcpack/source/image.h